CS350/full_adder_nand.v
module full_adder_nand(S, Cout, A, B, Cin);
input A, B, Cin;
output S, Cout;
wire w1, w2, w3, w4, w5, w6, w7;

nand midNand(w1, A, B);
nand topNand(w2, w1, A);
nand bottomNand(w3, w1, B);

nand thirdlevNand(w4, w2, w3);
nand fourthlevNand(w5, Cin, w4);

nand fiveTopNand(w6, w4, w5);
nand fiveMidNand(w7, Cin, w5);


nand(S, w6, w7);
nand(Cout, w5, w1);
endmodule

CS350/full_adder_tb.v
`timescale 1 ns / 100 ps
module full_adder_tb;
	reg A, B, Cin;
	wire S, Cout;
	full_adder_nand adder(.A(A), .B(B), .Cin(Cin), .S(S), .Cout(Cout));

	initial begin
		A = 0;
		B = 0;
		Cin = 0;

		#80;

		$finish;

	end

	always 
		#10 A = ~A;
	always
		#20 B = ~B;
	always
		#40 Cin = ~Cin;

	always @(A, B, Cin) begin
		#1;
		$display("A:%b, B:%b, Cin:%b => S:%b, Cout:%b", A, B, Cin, S, Cout);
	end
	
	initial begin
		$dumpfile("testwave.vcd");
		$dumpvars(0, full_adder_tb);
	end
endmodule

CS350/testwave.vcd
$date
	Fri Jan 24 03:13:06 2025
$end
$version
	Icarus Verilog
$end
$timescale
	100ps
$end
$scope module full_adder_tb $end
$var wire 1 ! S $end
$var wire 1 " Cout $end
$var reg 1 # A $end
$var reg 1 $ B $end
$var reg 1 % Cin $end
$scope module adder $end
$var wire 1 # A $end
$var wire 1 $ B $end
$var wire 1 % Cin $end
$var wire 1 " Cout $end
$var wire 1 ! S $end
$var wire 1 & w1 $end
$var wire 1 ' w2 $end
$var wire 1 ( w3 $end
$var wire 1 ) w4 $end
$var wire 1 * w5 $end
$var wire 1 + w6 $end
$var wire 1 , w7 $end
$upscope $end
$upscope $end
$enddefinitions $end
#0
$dumpvars
1,
1+
1*
0)
1(
1'
1&
0%
0$
0#
0"
0!
$end
#100
1!
0+
1)
0'
1#
#200
1'
0(
0#
1$
#300
0!
1+
0)
1(
1"
0&
1'
1#
#400
0"
1!
1&
0,
0#
0$
1%
#500
0!
1,
1"
0*
1+
1)
0'
1#
#600
1'
0(
0#
1$
#700
1!
0,
1*
0)
1(
0&
1'
1#
#800
0"
0!
1&
1,
0#
0$
0%
